.gitignore
.travis.yml
MANIFEST.in
README.rst
base.cfg
bootstrap.sh
buildout.cfg
plone-4.3.x.cfg
plone-5.0.x.cfg
plone-5.1.x.cfg
plone-5.2.x.cfg
setup.cfg
setup.py
travis.cfg
versions.cfg
docs/HISTORY.txt
docs/INSTALL.txt
docs/LICENSE.GPL
docs/LICENSE.txt
wildcard/__init__.py
wildcard.media.egg-info/PKG-INFO
wildcard.media.egg-info/SOURCES.txt
wildcard.media.egg-info/dependency_links.txt
wildcard.media.egg-info/entry_points.txt
wildcard.media.egg-info/namespace_packages.txt
wildcard.media.egg-info/not-zip-safe
wildcard.media.egg-info/requires.txt
wildcard.media.egg-info/top_level.txt
wildcard/media/__init__.py
wildcard/media/async_support.py
wildcard/media/behavior.py
wildcard/media/config.py
wildcard/media/configure.zcml
wildcard/media/content.py
wildcard/media/convert.py
wildcard/media/exportimport.py
wildcard/media/indexers.py
wildcard/media/interfaces.py
wildcard/media/pasync.py
wildcard/media/permissions.py
wildcard/media/primary.py
wildcard/media/profiles.zcml
wildcard/media/settings.py
wildcard/media/subscribers.py
wildcard/media/tasks.py
wildcard/media/testing.py
wildcard/media/upgrades.py
wildcard/media/youtube.py
wildcard/media/Extensions/Install.py
wildcard/media/browser/__init__.py
wildcard/media/browser/configure.zcml
wildcard/media/browser/forms.py
wildcard/media/browser/syndication.py
wildcard/media/browser/views.py
wildcard/media/browser/widget.py
wildcard/media/browser/static/.bowerrc
wildcard/media/browser/static/.gitignore
wildcard/media/browser/static/Gruntfile.js
wildcard/media/browser/static/Makefile
wildcard/media/browser/static/bower.json
wildcard/media/browser/static/config.js
wildcard/media/browser/static/integration-p4.js
wildcard/media/browser/static/integration.js
wildcard/media/browser/static/package.json
wildcard/media/browser/static/components/.gitignore
wildcard/media/browser/static/components/mediaelement/.bower.json
wildcard/media/browser/static/components/mediaelement/README.md
wildcard/media/browser/static/components/mediaelement/bower.json
wildcard/media/browser/static/components/mediaelement/build/background.png
wildcard/media/browser/static/components/mediaelement/build/bigplay.fw.png
wildcard/media/browser/static/components/mediaelement/build/bigplay.png
wildcard/media/browser/static/components/mediaelement/build/bigplay.svg
