Metadata-Version: 2.1
Name: wildcard.media
Version: 2.1.0
Summary: HTML5 audio and video integration with plone
Home-page: https://github.com/collective/wildcard.media
Author: Nathan Van Gheem
Author-email: nathan@vangheem.us
License: GPL
Keywords: video audio media plone tiny html5 mediaelement
Platform: UNKNOWN
Classifier: Framework :: Plone
Classifier: Programming Language :: Python
Classifier: Programming Language :: Python :: 2.7
Classifier: Programming Language :: Python :: 3.6
Classifier: Programming Language :: Python :: 3.7
Classifier: Framework :: Plone :: 4.3
Classifier: Framework :: Plone :: 5.0
Classifier: Framework :: Plone :: 5.1
Classifier: Framework :: Plone :: 5.2
Provides-Extra: test
Provides-Extra: youtube
